cell_data/__init__.py
cell_data/__version__.py
cell_data-0.0.0.dist-info/METADATA
cell_data-0.0.0.dist-info/WHEEL
cell_data-0.0.0.dist-info/top_level.txt
cell_data-0.0.0.dist-info/RECORD
